pyvariant/__init__.py
pyvariant/cli.py
pyvariant/constants.py
pyvariant/core.py
pyvariant/ensembl_cache.py
pyvariant/ensembl_release.py
pyvariant/files.py
pyvariant/parser.py
pyvariant/regex.py
pyvariant/sequence.py
pyvariant/tables.py
pyvariant/utils.py
pyvariant/variants.py
pyvariant/data/empty.fa
pyvariant/data/empty.fa.fai
pyvariant-2.3.0.dist-info/LICENSE
pyvariant-2.3.0.dist-info/METADATA
pyvariant-2.3.0.dist-info/WHEEL
pyvariant-2.3.0.dist-info/entry_points.txt
pyvariant-2.3.0.dist-info/top_level.txt
pyvariant-2.3.0.dist-info/zip-safe
pyvariant-2.3.0.dist-info/RECORD
