Metadata-Version: 2.1
Name: pyvariant
Version: 2.3.0
Summary: Map biological sequence variants (mutations) to their equivalent chromosome, cDNA, gene, exon, protein, and RNA positions.
Home-page: https://github.com/mattdoug604/pyvariant.git
Author: Matthew Douglas
Author-email: mattdoug604@gmail.com
Maintainer: Matthew Douglas
Maintainer-email: mattdoug604@gmail.com
License: MIT
Platform: any
Classifier: Development Status :: 4 - Beta
Classifier: Environment :: Console
Classifier: Intended Audience :: Science/Research
Classifier: License :: OSI Approved :: MIT License
Classifier: Operating System :: OS Independent
Classifier: Programming Language :: Python
Classifier: Programming Language :: Python :: 3
Classifier: Programming Language :: Python :: 3 :: Only
Classifier: Programming Language :: Python :: 3.8
Classifier: Programming Language :: Python :: 3.9
Classifier: Programming Language :: Python :: 3.10
Classifier: Programming Language :: Python :: 3.11
Classifier: Topic :: Scientific/Engineering
Classifier: Topic :: Scientific/Engineering :: Bio-Informatics
Requires-Python: >=3.8
License-File: LICENSE
Requires-Dist: appdirs
Requires-Dist: BioPython <1.80,>=1.73
Requires-Dist: gtfparse <=2.0.1
Requires-Dist: packaging
Requires-Dist: pandas
Requires-Dist: polars <0.17.0
Requires-Dist: pyarrow
Requires-Dist: pyfaidx
Provides-Extra: dev
Requires-Dist: black ; extra == 'dev'
Requires-Dist: flake8 ; extra == 'dev'
Requires-Dist: isort ; extra == 'dev'
Requires-Dist: mypy ; extra == 'dev'
Requires-Dist: pytest ; extra == 'dev'
Requires-Dist: pytest-cov ; extra == 'dev'
Requires-Dist: pytest-mock ; extra == 'dev'
Requires-Dist: twine ; extra == 'dev'
Requires-Dist: wheel ; extra == 'dev'
